CHANGES.txt
CONTRIBUTORS.txt
LICENSE.txt
MANIFEST.in
README.rst
TODO.txt
setup.py
djangorestframework_httpsignature.egg-info/PKG-INFO
djangorestframework_httpsignature.egg-info/SOURCES.txt
djangorestframework_httpsignature.egg-info/dependency_links.txt
djangorestframework_httpsignature.egg-info/requires.txt
djangorestframework_httpsignature.egg-info/top_level.txt
rest_framework_httpsignature/__init__.py
rest_framework_httpsignature/authentication.py
rest_framework_httpsignature/models.py
rest_framework_httpsignature/tests.py
rest_framework_httpsignature/views.py