Metadata-Version: 1.1
Name: djangorestframework-httpsignature
Version: 1.0.0
Summary: HTTP Signature support for Django REST framework
Home-page: https://github.com/etoccalino/django-rest-framework-httpsignature
Author: Elvio Toccalino
Author-email: me@etoccalino.com
License: LICENSE.txt
Platform: UNKNOWN
Classifier: Intended Audience :: Developers
Classifier: Development Status :: 5 - Production/Stable
Classifier: Environment :: Web Environment
Classifier: Framework :: Django
Classifier: Operating System :: OS Independent
Classifier: Programming Language :: Python :: 2.7
Classifier: License :: OSI Approved :: MIT License
Classifier: Topic :: Internet :: WWW/HTTP
Classifier: Topic :: Security
